odmlib/__init__.py
odmlib/define_loader.py
odmlib/descriptor.py
odmlib/document_loader.py
odmlib/loader.py
odmlib/ns_registry.py
odmlib/odm_element.py
odmlib/odm_loader.py
odmlib/odm_parser.py
odmlib/oid_index.py
odmlib/typed.py
odmlib/valueset.py
odmlib/ct_1_1_1/__init__.py
odmlib/ct_1_1_1/model.py
odmlib/dataset_1_0_1/__init__.py
odmlib/dataset_1_0_1/model.py
odmlib/define_2_0/__init__.py
odmlib/define_2_0/model.py
odmlib/define_2_0/rules/__init__.py
odmlib/define_2_0/rules/metadata_schema.py
odmlib/define_2_0/rules/oid_ref.py
odmlib/define_2_1/__init__.py
odmlib/define_2_1/model.py
odmlib/define_2_1/rules/__init__.py
odmlib/define_2_1/rules/metadata_schema.py
odmlib/define_2_1/rules/oid_ref.py
odmlib/odm_1_3_2/__init__.py
odmlib/odm_1_3_2/model.py
odmlib/odm_1_3_2/rules/__init__.py
odmlib/odm_1_3_2/rules/metadata_schema.py
odmlib/odm_1_3_2/rules/oid_ref.py
odmlib/odm_2_0/__init__.py
odmlib/odm_2_0/model.py
odmlib/odm_2_0/valueset.py
tests/__init__.py
tests/model_extended.py
tests/test_adminData.py
tests/test_attribute_order.py
tests/test_bottom_up.py
tests/test_cerberus_schemas_odm.py
tests/test_clinicalData.py
tests/test_codeList.py
tests/test_codeListItem.py
tests/test_codeList_define.py
tests/test_conditiondef.py
tests/test_conformance_checks_odm.py
tests/test_create_dataset.py
tests/test_create_odm.py
tests/test_define21_parser_metadata.py
tests/test_define_parser_metadata.py
tests/test_descriptor.py
tests/test_enumeratedItem.py
tests/test_extended_alias.py
tests/test_formDef.py
tests/test_insert_item.py
tests/test_itemDef.py
tests/test_itemDef_define.py
tests/test_itemGroupDef.py
tests/test_itemGroupDef_define.py
tests/test_itemGroupDef_define21.py
tests/test_json_from_xml.py
tests/test_metadataversion.py
tests/test_methodDef.py
tests/test_methodDef_check.py
tests/test_methodDef_define.py
tests/test_ns_registry.py
tests/test_odm_json_string_parser.py
tests/test_odm_loader.py
tests/test_odm_loader_define.py
tests/test_odm_loader_define_string.py
odmlib-0.1.4.dist-info/LICENSE.md
odmlib-0.1.4.dist-info/METADATA
odmlib-0.1.4.dist-info/WHEEL
odmlib-0.1.4.dist-info/top_level.txt
odmlib-0.1.4.dist-info/RECORD
