Metadata-Version: 2.1
Name: odmlib
Version: 0.1.4
Summary: Work with ODM as Python objects
Home-page: https://github.com/swhume/odmlib
Author: Sam Hume
Author-email: swhume@gmail.com
License: MIT
Platform: UNKNOWN
Requires-Dist: xmlschema (>=1.10.0)
Requires-Dist: validators (>=0.18.2)
Requires-Dist: Cerberus (>=1.3.4)
Requires-Dist: pathvalidate (>=2.3.1)
